m2aia/Dataset.py
m2aia/Generators.py
m2aia/ImageIO.py
m2aia/Library.py
m2aia/__init__.py
m2aia/bin/libCppMicroServices.so.2.99.0
m2aia/bin/libITKCommon-5.2.so.1
m2aia/bin/libITKIOBMP-5.2.so.1
m2aia/bin/libITKIOBioRad-5.2.so.1
m2aia/bin/libITKIOBruker-5.2.so.1
m2aia/bin/libITKIOGDCM-5.2.so.1
m2aia/bin/libITKIOGE-5.2.so.1
m2aia/bin/libITKIOGIPL-5.2.so.1
m2aia/bin/libITKIOHDF5-5.2.so.1
m2aia/bin/libITKIOIPL-5.2.so.1
m2aia/bin/libITKIOImageBase-5.2.so.1
m2aia/bin/libITKIOJPEG-5.2.so.1
m2aia/bin/libITKIOJPEG2000-5.2.so.1
m2aia/bin/libITKIOLSM-5.2.so.1
m2aia/bin/libITKIOMINC-5.2.so.1
m2aia/bin/libITKIOMRC-5.2.so.1
m2aia/bin/libITKIOMeta-5.2.so.1
m2aia/bin/libITKIONIFTI-5.2.so.1
m2aia/bin/libITKIONRRD-5.2.so.1
m2aia/bin/libITKIOPNG-5.2.so.1
m2aia/bin/libITKIOStimulate-5.2.so.1
m2aia/bin/libITKIOTIFF-5.2.so.1
m2aia/bin/libITKIOVTK-5.2.so.1
m2aia/bin/libITKMetaIO-5.2.so.1
m2aia/bin/libITKNrrdIO-5.2.so.1
m2aia/bin/libITKSmoothing-5.2.so.1
m2aia/bin/libITKStatistics-5.2.so.1
m2aia/bin/libITKTransform-5.2.so.1
m2aia/bin/libITKniftiio-5.2.so.1
m2aia/bin/libITKznz-5.2.so.1
m2aia/bin/libM2aiaCore.so
m2aia/bin/libMitkAlgorithmsExt.so
m2aia/bin/libMitkCore.so
m2aia/bin/libMitkDICOM.so
m2aia/bin/libMitkDICOMQI.so
m2aia/bin/libMitkDataTypesExt.so
m2aia/bin/libMitkDocker.so
m2aia/bin/libMitkElastix.so
m2aia/bin/libMitkMultilabel.so
m2aia/bin/libMitkSceneSerializationBase.so
m2aia/bin/libPocoFoundation.so.92
m2aia/bin/libann.so.1
m2aia/bin/libboost_filesystem.so.1.80.0
m2aia/bin/libdcmdata.so.17
m2aia/bin/libgdcmCommon.so.3.0
m2aia/bin/libgdcmDICT.so.3.0
m2aia/bin/libgdcmDSED.so.3.0
m2aia/bin/libgdcmIOD.so.3.0
m2aia/bin/libgdcmMSFF.so.3.0
m2aia/bin/libgdcmcharls.so.2
m2aia/bin/libgdcmexpat.so.2.0
m2aia/bin/libgdcmjpeg12.so.3.0
m2aia/bin/libgdcmjpeg16.so.3.0
m2aia/bin/libgdcmjpeg8.so.3.0
m2aia/bin/libgdcmopenjp2.so.7
m2aia/bin/libgdcmuuid.so.3.0
m2aia/bin/libgdcmzlib.so.3.0
m2aia/bin/libhdf5.so.10.2.0
m2aia/bin/libhdf5_cpp.so.10.2.0
m2aia/bin/libitkNetlibSlatec-5.2.so.1
m2aia-0.5.10.dist-info/LICENCE
m2aia-0.5.10.dist-info/METADATA
m2aia-0.5.10.dist-info/WHEEL
m2aia-0.5.10.dist-info/top_level.txt
m2aia-0.5.10.dist-info/RECORD
