Metadata-Version: 2.1
Name: m2aia
Version: 0.5.10
Summary: Provide interfaces for M2aia.
Home-page: https://m2aia.github.io/m2aia
Author: Jonas Cordes
Author-email: j.cordes@hs-mannheim.de
Project-URL: Bug Tracker, https://github.com/m2aia/pym2aia/issues
Classifier: Programming Language :: Python :: 3.8
Classifier: License :: OSI Approved :: BSD License
Classifier: Operating System :: Unix
Classifier: Operating System :: Microsoft :: Windows
Classifier: Topic :: Scientific/Engineering :: Image Processing
Classifier: Development Status :: 3 - Alpha
Requires-Python: >=3.8
License-File: LICENCE
Requires-Dist: wheel
Requires-Dist: numpy
Requires-Dist: SimpleITK
Requires-Dist: wget
